mlutil/__init__.py
mlutil/_util/__init__.py
mlutil/_util/_util.py
mlutil/eval/__init__.py
mlutil/eval/_cv.py
mlutil/model/__init__.py
mlutil/model/_pygam.py
mlutil/model/_statsgam.py
mlutil/transform/__init__.py
mlutil/transform/_encoder.py
mlutil/transform/_scaler.py
mlutil/transform/_selector.py
mlutil/tune/__init__.py
tests/__init__.py
tests/conftest.py
tests/test_eval.py
tests/test_gam.py
tests/test_stats_gam.py
tests/test_transform.py
mlutil-0.1.15.dist-info/LICENSE
mlutil-0.1.15.dist-info/METADATA
mlutil-0.1.15.dist-info/WHEEL
mlutil-0.1.15.dist-info/entry_points.txt
mlutil-0.1.15.dist-info/top_level.txt
mlutil-0.1.15.dist-info/RECORD
