Metadata-Version: 2.1
Name: mlutil
Version: 0.1.15
Summary: A few useful tools for Machine Learning
Home-page: https://github.com/mysterious-ben/dutil
Author: Yaroslav Kopotilov
Author-email: UNKNOWN
License: Apache License, Version 2.0
Platform: UNKNOWN
Classifier: Intended Audience :: Developers
Classifier: License :: OSI Approved :: Apache Software License
Classifier: Operating System :: OS Independent
Classifier: Programming Language :: Python
Classifier: Programming Language :: Python :: 3.7
Classifier: Programming Language :: Python :: 3.8
Classifier: Topic :: Software Development :: Libraries :: Python Modules
Requires-Python: >=3.8
